<?xml version="1.0" encoding="UTF-8"?>
<objects serializationModel="Studio.02.03.00">
	<object class="AudioFile" id="{aec25e4e-96ea-4386-8eb8-3808f1c43331}">
		<property name="assetPath">
			<value>Clock.wav</value>
		</property>
		<property name="isStreaming">
			<value>true</value>
		</property>
		<property name="frequencyInKHz">
			<value>44.0999985</value>
		</property>
		<property name="channelCount">
			<value>2</value>
		</property>
		<property name="length">
			<value>13.5</value>
		</property>
		<relationship name="masterAssetFolder">
			<destination>{5bb7d8b0-9b25-4390-988d-8e3d35b4d90a}</destination>
		</relationship>
	</object>
</objects>
